neuro_mine/__init__.py
neuro_mine/main.py
neuro_mine/lib/__init__.py
neuro_mine/lib/convert_suite2p.py
neuro_mine/lib/file_handling.py
neuro_mine/lib/mine.py
neuro_mine/lib/model.py
neuro_mine/lib/processing.py
neuro_mine/lib/taylorDecomp.py
neuro_mine/lib/utilities.py
neuro_mine/scripts/__init__.py
neuro_mine/scripts/neuromine_fit.py
neuro_mine/scripts/neuromine_prediction.py
neuro_mine/ui/__init__.py
neuro_mine/ui/mine_predict.py
neuro_mine/ui/mine_train.py
neuro_mine/ui/predict_gui.py
neuro_mine/ui/resources_rc.py
neuro_mine/ui/train_gui.py
neuro_mine/ui/ui_utilities.py
neuro_mine/ui/widget.py
neuro_mine-0.8.2.dist-info/METADATA
neuro_mine-0.8.2.dist-info/WHEEL
neuro_mine-0.8.2.dist-info/entry_points.txt
neuro_mine-0.8.2.dist-info/top_level.txt
neuro_mine-0.8.2.dist-info/RECORD
