Metadata-Version: 2.4
Name: neuro_mine
Version: 0.8.2
Summary: Identifies the contribution of behavioural and stimulus parameters to neural activity
Author-email: Danica Matovic <matovic.5@osu.edu>, Martin Haesemeyer <haesemeyer.1@osu.edu>
Project-URL: Homepage, https://github.com/matovic5/neuro_mine
Requires-Dist: h5py==3.14.*
Requires-Dist: matplotlib==3.9.*
Requires-Dist: numba==0.60.*
Requires-Dist: numpy==1.26.*
Requires-Dist: pandas==2.3.*
Requires-Dist: PySide6==6.7.3
Requires-Dist: scipy==1.13.*
Requires-Dist: tensorflow<=2.15.1
Requires-Dist: upsetplot==0.9.*
Requires-Dist: scikit-learn==1.6.*
Requires-Dist: urllib3==1.26.6
